setup.py
procblock/__init__.py
procblock/builtins.py
procblock/daemon.py
procblock/mainfunctions.py
procblock/processing.py
procblock/procyaml.py
procblock.egg-info/PKG-INFO
procblock.egg-info/SOURCES.txt
procblock.egg-info/dependency_links.txt
procblock.egg-info/requires.txt
procblock.egg-info/top_level.txt
procblock/run/__init__.py
procblock/run/code_python.py
procblock/run/running.py