Metadata-Version: 1.0
Name: procblock
Version: 2010.10.15.0
Summary: problock is a logic and data tag processor and hardended execution environment.
Home-page: http://ge01f.com/demo/monitor/
Author: Geoff Howland
Author-email: geoff@gmail.com
License: MIT
Keywords: tag processor logic data thread management execution
Platform: UNKNOWN
Classifier: Development Status :: 4 - Beta
Classifier: Environment :: Console
Classifier: Intended Audience :: Developers
Classifier: Intended Audience :: Information Technology
Classifier: Intended Audience :: System Administrators
Classifier: License :: OSI Approved :: MIT License
Classifier: Natural Language :: English
Classifier: Operating System :: MacOS :: MacOS X
Classifier: Operating System :: POSIX :: BSD :: FreeBSD
Classifier: Operating System :: POSIX :: Linux
Classifier: Programming Language :: Python :: 2.6
Classifier: Topic :: System :: Distributed Computing
Classifier: Topic :: System :: Installation/Setup
Classifier: Topic :: System :: Logging
Classifier: Topic :: System :: Monitoring
Classifier: Topic :: System :: Systems Administration
